timediffusion/__init__.py
timediffusion/frameworks.py
timediffusion/layers.py
timediffusion/models.py
timediffusion/utils.py
timediffusion-0.4.1.dist-info/LICENSE
timediffusion-0.4.1.dist-info/METADATA
timediffusion-0.4.1.dist-info/WHEEL
timediffusion-0.4.1.dist-info/top_level.txt
timediffusion-0.4.1.dist-info/RECORD
