Metadata-Version: 2.1
Name: timediffusion
Version: 0.4.1
Summary: TimeDiffusion - Unified Framework for Multiple Time Series Tasks
Author-email: Shishkov Vladislav <shishkovve@mail.com>
Project-URL: Homepage, https://github.com/timetoai/TimeDiffusion
Project-URL: Bug Tracker, https://github.com/timetoai/TimeDiffusion/issues
Classifier: Programming Language :: Python :: 3
Classifier: License :: OSI Approved :: MIT License
Classifier: Operating System :: OS Independent
Requires-Python: >=3.7
License-File: LICENSE
